common/decoder.v
module decoder
# (
    parameter WIDTH = 4,
    parameter OUTPUT_TYPE = 1
)
(
    input                      clk,
    input                      rst,
    input                      ack,
    input                      load,
    input 	   [WIDTH - 1:0] in,
    output reg     [WIDTH - 1:0] out
);

	always @ (posedge clock, negedge reset)
	  if (~reset)
            out <= {WIDTH { 1'b0 }};
          else if (load & ack)
            out <= in;
endmodule

common/arbiter.v
//получает на вход вектор запросов (1 где активный запрос)
//и базу - вектор, где 1 стоит на месте следующем за последним получившим доступ
//возвращает вектор, где 1 на получившем доступ

module arbiter (
	req, grant, base
);

parameter WIDTH = 16;

input [WIDTH-1:0] req;
output [WIDTH-1:0] grant;
input [WIDTH-1:0] base;

wire [2*WIDTH-1:0] double_req = {req,req};
wire [2*WIDTH-1:0] double_grant = double_req & ~(double_req-base);
assign grant = double_grant[WIDTH-1:0] | double_grant[2*WIDTH-1:WIDTH];
	
endmodule

common/shift_register.v
//сохраняет значение с циклическим сдвигом на 1 влево

module shift_register
# (
    parameter WIDTH = 4
)
(
    input                      clk,
    input                      rst,
    input                      load,
    input                      ack,
    input 	   [WIDTH - 1:0] in,
    output reg [WIDTH - 1:0] out
);
    reg [2 * WIDTH - 1:0] temp;

    always @ (posedge clk, negedge rst)
	if (~rst)
        out <= {{(WIDTH - 1){ 1'b0 }}, 1'b1};
      else if (load & ack) begin
        assign temp = {in, in} << 1;
    	assign out = temp[2 * WIDTH - 1: WIDTH];
      end
endmodule

common/rr_arbiter.v
module rr_arbiter(clk, resetb, ack, request, grant);
	parameter integer WIDTH = 4;
	input clk, resetb, ack;
	input [WIDTH - 1:0] request;
	output [WIDTH - 1:0] grant;

	wire [WIDTH - 1:0] next_base;
	wire [WIDTH - 1:0] grant_tmp;
	
	shift_register shifter(.clk(clk), .rst(resetb), .ack(ack), .load(1'b1), .in(grant_tmp), .out(next_base));

	arbiter arbiter(.req(request), .grant(grant_tmp), .base(next_base));

	decoder final_decoder(.clk(clk), .rst(resetb), .ack(ack), .load(1'b1), .in(grant_tmp), .out(grant));

endmodule

common/test.v
module test_arbiter;
      parameter integer WIDTH = 4;
	reg [WIDTH - 1:0] request;
	reg rst, clk, ack;
	wire [WIDTH - 1:0] grant;

	rr_arbiter #(WIDTH) rr_arbiter(.clk(clk), .resetb(rst), .ack(ack), .request(request), .grant(grant));
	

      always #1
            clk = !clk;

	initial
		begin
			rst = 0;
			ack = 0;
			
			#10;
			rst = 1;
			
			request = 4'b1010;
			ack = 1;
			#100;

			rst = 0;
			ack = 0;
			#10;
			rst = 1;
			request = 4'b0111;
			ack = 1;
			#100;

			rst = 0;
			ack = 0;
			#10;
			rst = 1;
			request=4'b1000;
			ack = 1;
			#100;

		end

	always@(request)
		$monitor("\n\tREQUEST VECTOR: %b\tGRANT VECTOR: %b\n",request,grant );

      initial begin 
            $dumpfile("dump.vcd");
            $dumpvars(1);
      end

endmodule

common/dump.vcd
$date
	Sat Nov  5 06:32:07 2022
$end
$version
	Icarus Verilog
$end
$timescale
	1s
$end
$scope module test_arbiter $end
$var wire 4 ! grant [3:0] $end
$var parameter 32 " WIDTH $end
$var reg 1 # ack $end
$var reg 1 $ clk $end
$var reg 4 % request [3:0] $end
$var reg 1 & rst $end
$upscope $end
$enddefinitions $end
$comment Show the parameter values. $end
$dumpall
b100 "
$end
#0
$dumpvars
0&
bx %
0$
0#
b0 !
$end
#1
1$
#2
0$
1#
b1010 %
1&
#3
b10 !
1$
#4
0$
#5
b1000 !
1$
#6
0$
0#
#7
1$
#8
0$
b111 %
#9
1$
#10
0$
1#
#11
b1 !
1$
#12
0$
#13
b10 !
1$
#14
0$
0#
#15
1$
#16
0$
b1000 %
#17
1$
#18
0$
1#
#19
b1000 !
1$
